MANIFEST.in
README.rst
setup.py
toolman/__init__.py
toolman/debug_utils.py
toolman/img_utils.py
toolman/misc_utils.py
toolman/process_block.py
toolman/pytorch_utils.py
toolman/vis_utils.py
toolman.egg-info/PKG-INFO
toolman.egg-info/SOURCES.txt
toolman.egg-info/dependency_links.txt
toolman.egg-info/not-zip-safe
toolman.egg-info/requires.txt
toolman.egg-info/top_level.txt