Metadata-Version: 1.0
Name: toolman
Version: 0.1.14
Summary: Python utility tools for research
Home-page: https://github.com/bohaohuang/toolman
Author: bohaohuang
Author-email: hbhzhuce@gmail.com
License: MIT
Platform: UNKNOWN
